
{"_id":{"$oid":"689b9333ba618869e4bc4b80"},"title":"Archives Of: DEPROF","slug":"deprof_archive","createdAt":{"$date":"2025-08-12T19:17:07.217Z"},"__v":0}
{"_id":{"$oid":"689b9333ba618869e4bc4b81"},"title":"contact_notfound","slug":"contact_notfound","createdAt":{"$date":"2025-08-12T19:17:07.217Z"},"__v":0}
{"_id":{"$oid":"689b9333ba618869e4bc4b82"},"title":"Archives Of: Abdul M. Yahaya","slug":"abdul_yahaya_Archive","createdAt":{"$date":"2025-08-12T19:17:07.218Z"},"__v":0}
{"_id":{"$oid":"689b9333ba618869e4bc4b83"},"title":"Archives Of: Engr. John Cee Onwualu, JP","slug":"Jefcon_more","createdAt":{"$date":"2025-08-12T19:17:07.218Z"},"__v":0}
{"_id":{"$oid":"689b9333ba618869e4bc4b84"},"title":"Monthly Archives: June 2025","slug":"archives_2025_june","createdAt":{"$date":"2025-08-12T19:17:07.218Z"},"__v":0}
{"_id":{"$oid":"689b9333ba618869e4bc4b85"},"title":"Monthly Archives: April 2025","slug":"archives_2025_april","createdAt":{"$date":"2025-08-12T19:17:07.218Z"},"__v":0}
{"_id":{"$oid":"689b9333ba618869e4bc4b86"},"title":"Monthly Archives: May 2024","slug":"archives_2024_may","createdAt":{"$date":"2025-08-12T19:17:07.219Z"},"__v":0}
{"_id":{"$oid":"689b9333ba618869e4bc4b87"},"title":"Monthly Archives: March 2024","slug":"archives_2024_march","createdAt":{"$date":"2025-08-12T19:17:07.219Z"},"__v":0}
{"_id":{"$oid":"689b9333ba618869e4bc4b88"},"title":"Monthly Archives: June 2024","slug":"archives_2024_june","createdAt":{"$date":"2025-08-12T19:17:07.219Z"},"__v":0}
{"_id":{"$oid":"689b9333ba618869e4bc4b89"},"title":"Monthly Archives: July 2024","slug":"archives_2024_july","createdAt":{"$date":"2025-08-12T19:17:07.219Z"},"__v":0}
{"_id":{"$oid":"689b9333ba618869e4bc4b8a"},"title":"Monthly Archives: January 2024","slug":"archives_2024_jan","createdAt":{"$date":"2025-08-12T19:17:07.219Z"},"__v":0}
{"_id":{"$oid":"689b9333ba618869e4bc4b8b"},"title":"Monthly Archives: February 2024","slug":"archives_2024_feb","createdAt":{"$date":"2025-08-12T19:17:07.219Z"},"__v":0}
{"_id":{"$oid":"689b9333ba618869e4bc4b8c"},"title":"Monthly Archives: April 2024","slug":"archives_2024_april","createdAt":{"$date":"2025-08-12T19:17:07.22Z"},"__v":0}
{"_id":{"$oid":"689b9333ba618869e4bc4b8d"},"title":"Monthly Archives: October 2023","slug":"archives_2023_oct","createdAt":{"$date":"2025-08-12T19:17:07.22Z"},"__v":0}
{"_id":{"$oid":"689b9333ba618869e4bc4b8e"},"title":"Monthly Archives: November 2023","slug":"archives_2023_nov","createdAt":{"$date":"2025-08-12T19:17:07.22Z"},"__v":0}
{"_id":{"$oid":"689b9333ba618869e4bc4b8f"},"title":"Monthly Archives: March 2023","slug":"archives_2023_march","createdAt":{"$date":"2025-08-12T19:17:07.22Z"},"__v":0}
{"_id":{"$oid":"689b9333ba618869e4bc4b90"},"title":"Monthly Archives: January 2023","slug":"archives_2023_jan","createdAt":{"$date":"2025-08-12T19:17:07.221Z"},"__v":0}
{"_id":{"$oid":"689b9333ba618869e4bc4b91"},"title":"Monthly Archives: February 2023","slug":"archives_2023_feb","createdAt":{"$date":"2025-08-12T19:17:07.221Z"},"__v":0}
{"_id":{"$oid":"689b9333ba618869e4bc4b92"},"title":"Monthly Archives: December 2023","slug":"archives_2023_dec","createdAt":{"$date":"2025-08-12T19:17:07.221Z"},"__v":0}
{"_id":{"$oid":"689b9333ba618869e4bc4b93"},"title":"Monthly Archives: September 2022","slug":"archives_2022_sept","createdAt":{"$date":"2025-08-12T19:17:07.221Z"},"__v":0}
{"_id":{"$oid":"689b9333ba618869e4bc4b94"},"title":"Monthly Archives: October 2022","slug":"archives_2022_oct","createdAt":{"$date":"2025-08-12T19:17:07.221Z"},"__v":0}
{"_id":{"$oid":"689b9333ba618869e4bc4b95"},"title":"Monthly Archives: November 2022","slug":"archives_2022_nov","createdAt":{"$date":"2025-08-12T19:17:07.221Z"},"__v":0}
{"_id":{"$oid":"689b9333ba618869e4bc4b96"},"title":"Monthly Archives: May 2022","slug":"archives_2022_may","createdAt":{"$date":"2025-08-12T19:17:07.222Z"},"__v":0}
{"_id":{"$oid":"689b9333ba618869e4bc4b97"},"title":"Monthly Archives: March 2022","slug":"archives_2022_march","createdAt":{"$date":"2025-08-12T19:17:07.222Z"},"__v":0}
{"_id":{"$oid":"689b9333ba618869e4bc4b98"},"title":"Monthly Archives: July 2022","slug":"archives_2022_july","createdAt":{"$date":"2025-08-12T19:17:07.222Z"},"__v":0}
{"_id":{"$oid":"689b9333ba618869e4bc4b99"},"title":"Monthly Archives: January 2022","slug":"archives_2022_jan","createdAt":{"$date":"2025-08-12T19:17:07.222Z"},"__v":0}
{"_id":{"$oid":"689b9333ba618869e4bc4b9a"},"title":"Monthly Archives: February 2022","slug":"archives_2022_feb","createdAt":{"$date":"2025-08-12T19:17:07.222Z"},"__v":0}
{"_id":{"$oid":"689b9333ba618869e4bc4b9b"},"title":"Monthly Archives: December 2022","slug":"archives_2022_dec","createdAt":{"$date":"2025-08-12T19:17:07.223Z"},"__v":0}
{"_id":{"$oid":"689b9333ba618869e4bc4b9c"},"title":"Monthly Archives: August 2022","slug":"archives_2022_august","createdAt":{"$date":"2025-08-12T19:17:07.223Z"},"__v":0}
{"_id":{"$oid":"689b9333ba618869e4bc4b9d"},"title":"Monthly Archives: April 2022","slug":"archives_2022_april","createdAt":{"$date":"2025-08-12T19:17:07.223Z"},"__v":0}
{"_id":{"$oid":"689b9333ba618869e4bc4b9e"},"title":"Monthly Archives: November 2021","slug":"archives_2021_nov","createdAt":{"$date":"2025-08-12T19:17:07.223Z"},"__v":0}
{"_id":{"$oid":"689b9333ba618869e4bc4b9f"},"title":"Monthly Archives: May 2021","slug":"archives_2021_may","createdAt":{"$date":"2025-08-12T19:17:07.223Z"},"__v":0}
{"_id":{"$oid":"689b9333ba618869e4bc4ba0"},"title":"Monthly Archives: June 2021","slug":"archives_2021_june","createdAt":{"$date":"2025-08-12T19:17:07.223Z"},"__v":0}
{"_id":{"$oid":"689b9333ba618869e4bc4ba1"},"title":"Monthly Archives: January 2021","slug":"archives_2021_jan","createdAt":{"$date":"2025-08-12T19:17:07.224Z"},"__v":0}
{"_id":{"$oid":"689b9333ba618869e4bc4ba2"},"title":"Monthly Archives: December 2021","slug":"archives_2021_dec","createdAt":{"$date":"2025-08-12T19:17:07.224Z"},"__v":0}
{"_id":{"$oid":"689b9333ba618869e4bc4ba3"},"title":"Monthly Archives: August 2021","slug":"archives_2021_august","createdAt":{"$date":"2025-08-12T19:17:07.224Z"},"__v":0}
{"_id":{"$oid":"689b9333ba618869e4bc4ba4"},"title":"Monthly Archives: April 2021","slug":"archives_2021_april","createdAt":{"$date":"2025-08-12T19:17:07.224Z"},"__v":0}
{"_id":{"$oid":"689b9333ba618869e4bc4ba5"},"title":"Monthly Archives: September 2020","slug":"archives_2020_sept","createdAt":{"$date":"2025-08-12T19:17:07.224Z"},"__v":0}
{"_id":{"$oid":"689b9333ba618869e4bc4ba6"},"title":"Monthly Archives: October 2020","slug":"archives_2020_oct","createdAt":{"$date":"2025-08-12T19:17:07.225Z"},"__v":0}
{"_id":{"$oid":"689b9333ba618869e4bc4ba7"},"title":"Monthly Archives: November 2020","slug":"archives_2020_nov","createdAt":{"$date":"2025-08-12T19:17:07.225Z"},"__v":0}
{"_id":{"$oid":"689b9333ba618869e4bc4ba8"},"title":"Monthly Archives: May 2020","slug":"archives_2020_may","createdAt":{"$date":"2025-08-12T19:17:07.225Z"},"__v":0}
{"_id":{"$oid":"689b9333ba618869e4bc4ba9"},"title":"Monthly Archives: July 2020","slug":"archives_2020_july","createdAt":{"$date":"2025-08-12T19:17:07.225Z"},"__v":0}
{"_id":{"$oid":"689b9333ba618869e4bc4baa"},"title":"Monthly Archives: August 2020","slug":"archives_2020_august","createdAt":{"$date":"2025-08-12T19:17:07.225Z"},"__v":0}
